{"name":"Little Head Starters","tagline":"","body":"![Little Head Starters](littleHeadStartersLogo.jpg)\r\n### Welcome to Little Head Starters\r\n\r\nChildren readily absorb information in the early years of their lives.\r\n\r\nLittle Head Starters is a parent/child interactive program for 2-6 year olds focussing on:\r\n\r\n* Alphabet recognition & phonics (sight words for advanced kids)\r\n* Number recognition & counting (simple mathematics for advanced)\r\n* Colours\r\n* Shapes\r\n* Clock\r\n* Calendar\r\n* Memory enhancement\r\n* Social skills, such as sharing, taking turns and following instructions through songs, games and activities.\r\n \r\n\r\nLittle Head Starters is a structured, fun, weekly program providing the opportunity for young children to be exposed to literacy and numeracy skills before they attend school.\r\n\r\nThe program also helps to develop your child's confidence with opportunities to speak in front of a small group, such as show & tell, and become a 'leader'. There are also many activities to help improve fine motor and gross motor skills.\r\n\r\nAll songs, games and activities are specifically designed to maximise learning.\r\n\r\nParent participation ensures that every child receives one-on-one attention whilst attending the session and can take home ideas and skills to continue learning at home. It is extremely rewarding to be actively involved in your child's development.\r\n\r\n\r\n***\r\n\r\n### \r\n**FIRST SESSION FREE!**\r\n\r\nCommencing Friday 21 February 2014\r\nLimited places available.  Book early to avoid disappointment.\r\n**Location:** Glen Waverley/ Wheelers Hill\r\n**Contact** 0449 112 636 for further details.","google":"","note":"Don't delete this file! It's used internally to help with page regeneration."}